drive_events/__init__.py
drive_events/broker.py
drive_events/core.py
drive_events/types.py
drive_events/utils.py
drive_events-0.0.1.dev4.dist-info/LICENSE
drive_events-0.0.1.dev4.dist-info/METADATA
drive_events-0.0.1.dev4.dist-info/WHEEL
drive_events-0.0.1.dev4.dist-info/top_level.txt
drive_events-0.0.1.dev4.dist-info/RECORD
