Metadata-Version: 2.1
Name: drive-events
Version: 0.0.1.dev4
Summary: Build event-driven workflows with python functions
Home-page: https://github.com/memodb-io/drive-events
Author: JianbaiYe
Classifier: Programming Language :: Python :: 3
Classifier: License :: OSI Approved :: MIT License
Classifier: Operating System :: OS Independent
Requires-Python: >=3.9
License-File: LICENSE
